{
  "status": "success",
  "summary": "PLAN_CODE phase completed successfully for story US-002.",
  "actions": [
    {
      "action": "write_file",
      "file_path": "tests/test_formatters.py",
      "status": "success",
      "summary": "Created new test file with pytest tests for the `format_duration` utility function."
    },
    {
      "action": "run_shell_command",
      "command": "./.venv/bin/pytest tests/test_formatters.py -v",
      "status": "failure",
      "summary": "Initial test run failed due to incorrect logic for negative numbers in the `format_duration` function."
    },
    {
      "action": "replace",
      "file_path": "src/utils/formatters.py",
      "status": "success",
      "summary": "Corrected the logic in the `format_duration` function to handle negative inputs correctly."
    },
    {
      "action": "run_shell_command",
      "command": "./.venv/bin/pytest tests/test_formatters.py -v",
      "status": "success",
      "summary": "All 6 tests for `format_duration` passed after fixing the implementation."
    }
  ],
  "next_phase": "TDD_GREEN"
}